pmlearn/__init__.py
pmlearn/base.py
pmlearn/exceptions.py
pmlearn/gaussian_process/__init__.py
pmlearn/gaussian_process/gpc.py
pmlearn/gaussian_process/gpr.py
pmlearn/gaussian_process/kernels.py
pmlearn/gaussian_process/tests/__init__.py
pmlearn/gaussian_process/tests/test_gpr.py
pmlearn/linear_model/__init__.py
pmlearn/linear_model/base.py
pmlearn/linear_model/logistic.py
pmlearn/linear_model/tests/__init__.py
pmlearn/linear_model/tests/test_base.py
pmlearn/linear_model/tests/test_logistic.py
pmlearn/mixture/__init__.py
pmlearn/mixture/dirichlet_process.py
pmlearn/mixture/gaussian_mixture.py
pmlearn/mixture/util.py
pmlearn/mixture/tests/__init__.py
pmlearn/mixture/tests/test_dirichlet_process.py
pmlearn/mixture/tests/test_gaussian_mixture.py
pmlearn/naive_bayes/__init__.py
pmlearn/naive_bayes/naive_bayes.py
pmlearn/naive_bayes/tests/__init__.py
pmlearn/naive_bayes/tests/test_naive_bayes.py
pmlearn/neural_network/__init__.py
pmlearn/neural_network/multilayer_perceptron.py
pmlearn/neural_network/tests/__init__.py
pmlearn/neural_network/tests/test_mutlilayer_perceptron.py
pmlearn/tests/__init__.py
pmlearn/tests/test_base.py
pymc_learn-0.0.1rc3.dist-info/AUTHORS.txt
pymc_learn-0.0.1rc3.dist-info/LICENSE
pymc_learn-0.0.1rc3.dist-info/METADATA
pymc_learn-0.0.1rc3.dist-info/WHEEL
pymc_learn-0.0.1rc3.dist-info/top_level.txt
pymc_learn-0.0.1rc3.dist-info/RECORD
