Metadata-Version: 2.1
Name: pymc-learn
Version: 0.0.1rc3
Summary: Practical Probabilistic Machine Learning in Python
Home-page: https://github.com/pymc-learn/pymc-learn
Author: Pymc-Learn Team
Author-email: daniel.emaasit@gmail.com
License: Copyright (c) 2019 Pymc-learn Developers
Requires-Dist: future (>=0.16.0)
Requires-Dist: joblib (>=0.11)
Requires-Dist: matplotlib (>=2.1.1)
Requires-Dist: numpy (>=1.13.1)
Requires-Dist: numpydoc (>=0.7.0)
Requires-Dist: pandas (>=0.21.1)
Requires-Dist: pymc3 (>=3.4.1)
Requires-Dist: scikit-learn (>=0.19.1)
Requires-Dist: scipy (>=1.0.0)
Requires-Dist: seaborn (>=0.8.1)
Requires-Dist: six (>=1.10.0)
Requires-Dist: theano (>=1.0.0)
Requires-Dist: tqdm (>=4.8.4)
